simplepytorch/__init__.py
simplepytorch/__main__.py
simplepytorch/api.py
simplepytorch/cache.py
simplepytorch/cmdline.py
simplepytorch/early_stopping.py
simplepytorch/feedforward.py
simplepytorch/logging_tools.py
simplepytorch/metrics.py
simplepytorch/plot_perf.py
simplepytorch/raytunelib.py
simplepytorch/result.py
simplepytorch/trainlib.py
simplepytorch/datasets/BBBC038v1_microscopy.py
simplepytorch/datasets/__init__.py
simplepytorch/datasets/_shared.py
simplepytorch/datasets/chexpert.py
simplepytorch/datasets/drive.py
simplepytorch/datasets/eyepacs.py
simplepytorch/datasets/glob_image_dir.py
simplepytorch/datasets/idrid.py
simplepytorch/datasets/intel_mobileodt_cervical.py
simplepytorch/datasets/kimeye.py
simplepytorch/datasets/messidor.py
simplepytorch/datasets/pickled_dicts.py
simplepytorch/datasets/preprocess.py
simplepytorch/datasets/qualdr.py
simplepytorch/datasets/rite.py
simplepytorch/datasets/train_val_test_split.py
simplepytorch-1.0.0.data/scripts/simplepytorch
simplepytorch-1.0.0.data/scripts/simplepytorch_debug
simplepytorch-1.0.0.data/scripts/simplepytorch_plot
simplepytorch-1.0.0.dist-info/LICENSE
simplepytorch-1.0.0.dist-info/METADATA
simplepytorch-1.0.0.dist-info/WHEEL
simplepytorch-1.0.0.dist-info/top_level.txt
simplepytorch-1.0.0.dist-info/RECORD
