Metadata-Version: 2.1
Name: simplepytorch
Version: 1.0.0
Summary: Setup and train deep nets with PyTorch. Opinionated and Simple.
Home-page: https://github.com/adgaudio/simplepytorch
Author: Alex Gaudio
License: MIT
Platform: UNKNOWN
Classifier: License :: OSI Approved :: MIT License
Classifier: Programming Language :: Python :: 3.8
Requires-Dist: torchvision
Requires-Dist: torch
Requires-Dist: pretrainedmodels
Requires-Dist: pandas
Requires-Dist: numpy
Requires-Dist: configargparse
Requires-Dist: pillow
Requires-Dist: scikit-learn
Requires-Dist: matplotlib
Requires-Dist: efficientnet-pytorch
Requires-Dist: tables
Provides-Extra: dataset_qualdr
Requires-Dist: pyjq ; extra == 'dataset_qualdr'
Provides-Extra: ray
Requires-Dist: ray[default] ; extra == 'ray'
Requires-Dist: ray[tune] ; extra == 'ray'
